blc/__init__.py
blc/api.py
blc/categories_command.py
blc/conf_command.py
blc/handlers/__init__.py
blc/handlers/category.py
blc/handlers/exceptions.py
blc/handlers/project.py
blc/handlers/task.py
blc/projects_command.py
blc/tasks_command.py
blc-0.1.2.dist-info/WHEEL
blc-0.1.2.dist-info/METADATA
blc-0.1.2.dist-info/RECORD
