Metadata-Version: 2.1
Name: blc
Version: 0.1.2
Summary: 
Author: Dimitrios Strantsalis
Author-email: dstrants@gmail.com
Requires-Python: >=3.6,<4.0
Classifier: Programming Language :: Python :: 3
Classifier: Programming Language :: Python :: 3.6
Classifier: Programming Language :: Python :: 3.7
Classifier: Programming Language :: Python :: 3.8
Requires-Dist: cleo (>=0.8.1,<0.9.0)
Requires-Dist: pendulum (>=2.1.0,<3.0.0)
Requires-Dist: requests (>=2.23.0,<3.0.0)
Requires-Dist: rich (>=1.3.1,<2.0.0)
Requires-Dist: tinydb (>=4.1.1,<5.0.0)
